jensey/__init__.py
jensey/__main__.py
jensey-1.0.dist-info/METADATA
jensey-1.0.dist-info/WHEEL
jensey-1.0.dist-info/entry_points.txt
jensey-1.0.dist-info/top_level.txt
jensey-1.0.dist-info/RECORD
