Metadata-Version: 2.1
Name: jensey
Version: 1.0
Summary: Imitate Shakespeare quote.
Home-page: https://sdfgsad.com
Author: Gao Tianchi
Author-email: 6159984@gmail.com
License: UNKNOWN
Platform: UNKNOWN
Requires-Dist: setuptools
